LICENSE
README.md
setup.py
HttpMax/__init__.py
HttpMax/__version__.py
HttpMax/_api.py
HttpMax/_auth.py
HttpMax/_client.py
HttpMax/_compat.py
HttpMax/_config.py
HttpMax/_content.py
HttpMax/_decoders.py
HttpMax/_exceptions.py
HttpMax/_main.py
HttpMax/_models.py
HttpMax/_multipart.py
HttpMax/_status_codes.py
HttpMax/_types.py
HttpMax/_urlparse.py
HttpMax/_urls.py
HttpMax/_utils.py
HttpMax.egg-info/PKG-INFO
HttpMax.egg-info/SOURCES.txt
HttpMax.egg-info/dependency_links.txt
HttpMax.egg-info/not-zip-safe
HttpMax.egg-info/requires.txt
HttpMax.egg-info/top_level.txt