Metadata-Version: 2.1
Name: HttpMax
Version: 1.2
Summary: Python HTTP Client for All.
Home-page: https://github.com/shayanheidari01/HttpMax
Author: Shayan Heidari
Author-email: me@shayanheidari.info
License: Apache 2.0
Project-URL: Documentation, https://github.com/shayanheidari01/HttpMax
Project-URL: Source, https://github.com/shayanheidari01/HttpMax
Classifier: Development Status :: 5 - Production/Stable
Classifier: Environment :: Web Environment
Classifier: Intended Audience :: Developers
Classifier: License :: OSI Approved :: Apache Software License
Classifier: Natural Language :: English
Classifier: Operating System :: OS Independent
Classifier: Programming Language :: Python
Classifier: Programming Language :: Python :: 3
Classifier: Programming Language :: Python :: 3.7
Classifier: Programming Language :: Python :: 3.8
Classifier: Programming Language :: Python :: 3.9
Classifier: Programming Language :: Python :: 3.10
Classifier: Programming Language :: Python :: 3.11
Classifier: Programming Language :: Python :: 3 :: Only
Classifier: Programming Language :: Python :: Implementation :: CPython
Classifier: Programming Language :: Python :: Implementation :: PyPy
Classifier: Topic :: Internet :: WWW/HTTP
Classifier: Topic :: Software Development :: Libraries
Requires-Python: >=3.7, <4
Provides-Extra: brotli
Provides-Extra: cli
Provides-Extra: http2
Provides-Extra: socks
License-File: LICENSE
